LICENSE
MANIFEST.in
README.rst
setup.py
quicktick/__init__.py
quicktick/config.py
quicktick/datasource.py
quicktick/formatter.py
quicktick/main.py
quicktick/symbol.py
quicktick.egg-info/PKG-INFO
quicktick.egg-info/SOURCES.txt
quicktick.egg-info/dependency_links.txt
quicktick.egg-info/entry_points.txt
quicktick.egg-info/requires.txt
quicktick.egg-info/top_level.txt