Metadata-Version: 1.2
Name: quicktick
Version: 0.2.5
Summary: Simple cryptocurrency ticker
Home-page: https://github.com/Xophmeister/quicktick
Author: Christopher Harrison
Author-email: UNKNOWN
License: GPLv3
Keywords: cryptocurrency ticker
Platform: UNKNOWN
Classifier: Development Status :: 4 - Beta
Classifier: Intended Audience :: End Users/Desktop
Classifier: Intended Audience :: Financial and Insurance Industry
Classifier: License :: OSI Approved :: GNU General Public License v3 or later (GPLv3+)
Classifier: Operating System :: POSIX
Classifier: Programming Language :: Python :: 3.6
Requires-Python: >=3.6
